connectomics/common/array.py
connectomics/common/array_test.py
connectomics/common/async_lib.py
connectomics/common/beam_utils.py
connectomics/common/beam_utils_test.py
connectomics/common/binaries.py
connectomics/common/bounding_box.py
connectomics/common/bounding_box_test.py
connectomics/common/box_generator.py
connectomics/common/box_generator_test.py
connectomics/common/counters.py
connectomics/common/counters_test.py
connectomics/common/file.py
connectomics/common/file_test.py
connectomics/common/geom_utils.py
connectomics/common/gin_utils.py
connectomics/common/gin_utils_test.py
connectomics/common/graph_utils.py
connectomics/common/import_util.py
connectomics/common/io_utils.py
connectomics/common/io_utils_test.py
connectomics/common/jax_utils.py
connectomics/common/jax_utils_test.py
connectomics/common/metadata_utils.py
connectomics/common/object_utils.py
connectomics/common/opencv_utils.py
connectomics/common/opencv_utils_test.py
connectomics/common/sharding.py
connectomics/common/ts_utils.py
connectomics/common/tuples.py
connectomics/common/tuples_test.py
connectomics/common/union_find.py
connectomics/common/union_find_test.py
connectomics/common/utils.py
connectomics/common/utils_test.py
connectomics/jax/checkpoint.py
connectomics/jax/config_util.py
connectomics/jax/config_util_test.py
connectomics/jax/grain_util.py
connectomics/jax/grain_util_test.py
connectomics/jax/metrics.py
connectomics/jax/metrics_test.py
connectomics/jax/parameter_replacement_util.py
connectomics/jax/parameter_replacement_util_test.py
connectomics/jax/training.py
connectomics/jax/util.py
connectomics/jax/util_test.py
connectomics/jax/inputs/tensorloader.py
connectomics/jax/inputs/tensorloader_test.py
connectomics/jax/models/activation.py
connectomics/jax/models/attention.py
connectomics/jax/models/attention_test.py
connectomics/jax/models/convstack.py
connectomics/jax/models/initializer.py
connectomics/jax/models/normalization.py
connectomics/jax/models/normalization_test.py
connectomics-20250606.dist-info/licenses/LICENSE
connectomics-20250606.dist-info/METADATA
connectomics-20250606.dist-info/WHEEL
connectomics-20250606.dist-info/top_level.txt
connectomics-20250606.dist-info/RECORD
