Metadata-Version: 2.4
Name: connectomics
Version: 20250606
Summary: Common repository for connectomics-related libraries.
Home-page: https://github.com/google-research/connectomics
Author: Google Connectomics Team
Author-email: noreply@google.com
Requires-Python: >=3.6
License-File: LICENSE
Requires-Dist: absl-py
Requires-Dist: dataclasses-json>=0.5.6
Requires-Dist: edt
Requires-Dist: numpy
Requires-Dist: scikit-image
Requires-Dist: scipy
Requires-Dist: sofima
Provides-Extra: decorators
Requires-Dist: gin-config; extra == "decorators"
Requires-Dist: jax; extra == "decorators"
Requires-Dist: tensorstore; extra == "decorators"
Provides-Extra: materialize-tensor
Requires-Dist: apache-beam; extra == "materialize-tensor"
Requires-Dist: connectomics[decorators]; extra == "materialize-tensor"
Provides-Extra: segclr
Requires-Dist: tensorflow; extra == "segclr"
Requires-Dist: edward2; extra == "segclr"
Requires-Dist: scikit-learn; extra == "segclr"
Dynamic: license-file
